PhysPackage/_init_.py
PhysPackage-0.1.dist-info/METADATA
PhysPackage-0.1.dist-info/WHEEL
PhysPackage-0.1.dist-info/license.txt.txt
PhysPackage-0.1.dist-info/top_level.txt
PhysPackage-0.1.dist-info/RECORD
