Metadata-Version: 2.1
Name: PhysPackage
Version: 0.1
Summary: this is desription
Author: Aishik Sen
License-File: license.txt.txt
